bpydoc/__init__.py
bpydoc/pydoc.py
pydoc/__init__.py
pydoc/pydoc.py
bpydoc-1.12.43.dist-info/METADATA
bpydoc-1.12.43.dist-info/WHEEL
bpydoc-1.12.43.dist-info/top_level.txt
bpydoc-1.12.43.dist-info/RECORD
