Metadata-Version: 2.1
Name: bpydoc
Version: 1.12.43
Summary: Python package
Author: Alex
Author-email: hahamaxxx1@gmail.com
Requires-Python: >=3.7
Requires-Dist: groq
